vcf_to_duckdb/__init__.py
vcf_to_duckdb/__main__.py
vcf_to_duckdb/convert_utils.py
vcf_to_duckdb/merge_utils.py
vcf_to_duckdb-0.4.0.dist-info/METADATA
vcf_to_duckdb-0.4.0.dist-info/WHEEL
vcf_to_duckdb-0.4.0.dist-info/RECORD
