Metadata-Version: 2.1
Name: vcf-to-duckdb
Version: 0.4.0
Summary: Convert a VCF file to a DuckDB database
License: MIT
Author: Devin McCabe
Author-email: dmccabe@broadinstitute.org
Requires-Python: >=3.12,<4.0
Classifier: License :: OSI Approved :: MIT License
Classifier: Programming Language :: Python :: 3
Classifier: Programming Language :: Python :: 3.12
Classifier: Programming Language :: Python :: 3.13
Requires-Dist: bgzip (>=0.5.0,<0.6.0)
Requires-Dist: case-converter (>=1.1.0,<2.0.0)
Requires-Dist: duckdb (>=1.1.3,<2.0.0)
Requires-Dist: pandas (>=2.2.3,<3.0.0)
Requires-Dist: pyarrow (>=21.0.0,<22.0.0)
Requires-Dist: typer (>=0.15.1,<0.16.0)
